bestatic/__init__.py
bestatic/_version.py
bestatic/bestatic.py
bestatic/bestaticSitemap.py
bestatic/generator.py
bestatic/httpserver.py
bestatic/imageprocessor.py
bestatic/newcontent.py
bestatic/quickstart.py
bestatic/shortcodes.py
bestatic-0.0.36.dist-info/licenses/LICENSE
tests/README.md
tests/__init__.py
tests/conftest.py
tests/test_cli.py
tests/test_generator.py
tests/test_httpserver.py
tests/test_imageprocessor.py
tests/test_newcontent.py
tests/test_quickstart.py
tests/test_shortcodes.py
tests/test_sitemap.py
bestatic-0.0.36.dist-info/METADATA
bestatic-0.0.36.dist-info/WHEEL
bestatic-0.0.36.dist-info/entry_points.txt
bestatic-0.0.36.dist-info/top_level.txt
bestatic-0.0.36.dist-info/RECORD
