Metadata-Version: 2.4
Name: Bestatic
Version: 0.0.36
Summary: A simple but really powerful static-site generator
Home-page: https://www.bestaticpy.com/
Download-URL: https://github.com/tatsatb/bestatic/releases/latest
Author: Tatsat Banerjee
License: GPL-3.0-or-later
Project-URL: Bug Reports, https://github.com/tatsatb/bestatic/issues
Project-URL: Source, https://github.com/tatsatb/bestatic
Project-URL: Documentation, https://www.bestaticpy.com/docs/
Keywords: static-site-generator documentation blog website markdown jinja2
Classifier: Development Status :: 4 - Beta
Classifier: Intended Audience :: Developers
Classifier: Topic :: Internet :: WWW/HTTP :: Site Management
Classifier: Topic :: Software Development :: Build Tools
Classifier: Programming Language :: Python :: 3
Classifier: Programming Language :: Python :: 3.10
Classifier: Programming Language :: Python :: 3.11
Classifier: Programming Language :: Python :: 3.12
Classifier: Programming Language :: Python :: 3.13
Classifier: Programming Language :: Python :: 3.14
Classifier: Operating System :: OS Independent
Requires-Python: >=3.10
License-File: LICENSE
Requires-Dist: beautifulsoup4==4.14.3
Requires-Dist: chardet==5.2.0
Requires-Dist: Jinja2==3.1.6
Requires-Dist: Markdown==3.10
Requires-Dist: markdown-include==0.8.1
Requires-Dist: MarkupSafe==3.0.3
Requires-Dist: mkdocs-material==9.7.1
Requires-Dist: Pygments==2.19.2
Requires-Dist: python-frontmatter==1.1.0
Requires-Dist: PyYAML==6.0.3
Requires-Dist: soupsieve==2.8.1
Requires-Dist: text-unidecode==1.3
Requires-Dist: tomli==2.3.0
Requires-Dist: pytz==2025.2
Requires-Dist: feedgen==1.0.0
Requires-Dist: markdown-customblocks==1.5.4
Requires-Dist: pymdown-extensions==10.19.1
Requires-Dist: watchdog==6.0.0
Requires-Dist: Pillow==12.0.0
Requires-Dist: python-magic-bin==0.4.14; sys_platform == "win32"
Requires-Dist: python-magic==0.4.27; sys_platform != "win32"
Provides-Extra: dev
Requires-Dist: pytest==9.0.2; extra == "dev"
Requires-Dist: pytest-cov==3.0.0; extra == "dev"
Dynamic: author
Dynamic: classifier
Dynamic: description
Dynamic: description-content-type
Dynamic: download-url
Dynamic: home-page
Dynamic: keywords
Dynamic: license
Dynamic: license-file
Dynamic: project-url
Dynamic: provides-extra
Dynamic: requires-dist
Dynamic: requires-python
Dynamic: summary
